leruli/__init__.py
leruli/cli.py
leruli/graph.py
leruli/internal.py
leruli/misc.py
leruli/task.py
leruli/test.py
leruli-22.1.6.dist-info/METADATA
leruli-22.1.6.dist-info/WHEEL
leruli-22.1.6.dist-info/entry_points.txt
leruli-22.1.6.dist-info/top_level.txt
leruli-22.1.6.dist-info/RECORD
