Metadata-Version: 2.1
Name: leruli
Version: 22.1.6
Summary: Use leruli.com from command line and Python code.
Author: leruli.com
Author-email: info@leruli.com
License: UNKNOWN
Keywords: leruli
Platform: UNKNOWN
Classifier: Development Status :: 5 - Production/Stable
Classifier: Natural Language :: English
Classifier: Programming Language :: Python :: 3
Classifier: Programming Language :: Python :: 3.6
Classifier: Programming Language :: Python :: 3.7
Classifier: Programming Language :: Python :: 3.8
Requires-Python: >=3.6
Requires-Dist: Click (>=7.0)
Requires-Dist: requests
Requires-Dist: tabulate
Requires-Dist: minio
Requires-Dist: docker
Requires-Dist: tqdm (>=4.62.0)
Requires-Dist: aiobotocore
Requires-Dist: aiohttp
